cogload/__init__.py
cogload/loader.py
cogload-0.0.3.dist-info/licenses/LICENSE
cogload-0.0.3.dist-info/METADATA
cogload-0.0.3.dist-info/WHEEL
cogload-0.0.3.dist-info/top_level.txt
cogload-0.0.3.dist-info/RECORD
